ttoolly/__init__.py
ttoolly/for_runner.py
ttoolly/models.py
ttoolly/runner.py
ttoolly/testcases.py
ttoolly/html_report/__init__.py
ttoolly/html_report/report.py
ttoolly/html_report/templates/_index.html
ttoolly/management/__init__.py
ttoolly/management/commands/__init__.py
ttoolly/management/commands/generate_model_fixture.py
ttoolly/management/commands/prepare_files_for_tests.py
ttoolly/management/commands/set_all_password.py
ttoolly/management/commands/udumpdata.py
ttoolly/utils/__init__.py
ttoolly/utils/decorators.py
ttoolly/utils/utils.py
ttoolly-0.38.0.dist-info/METADATA
ttoolly-0.38.0.dist-info/WHEEL
ttoolly-0.38.0.dist-info/top_level.txt
ttoolly-0.38.0.dist-info/RECORD
