Metadata-Version: 2.1
Name: ttoolly
Version: 0.38.0
Summary: Django test tools
Author: Polina Efremova
Author-email: pefremova@gmail.com
Keywords: django,testing,test tool
Classifier: Framework :: Django
Classifier: Programming Language :: Python
Requires-Dist: lxml
Requires-Dist: chardet
Requires-Dist: Pillow
Requires-Dist: rstr
Requires-Dist: future
Requires-Dist: freezegun
Requires-Dist: pytz
Requires-Dist: boolean.py >=3.6
Requires-Dist: functools32 ; python_version < "3"
